PyListenerTool/__init__.py
pylistenertool-26.1.11.dist-info/METADATA
pylistenertool-26.1.11.dist-info/WHEEL
pylistenertool-26.1.11.dist-info/licenses/LICENSE
pylistenertool-26.1.11.dist-info/RECORD
