Metadata-Version: 2.4
Name: PyListenerTool
Version: 26.1.11
Summary: A lightweight event listener system for Python classes that auto-generates documentation.
License: MIT
License-File: LICENSE
Keywords: event-driven,listener,observer-pattern,pub-sub,event-management,event-documentation
Author: qiufeng
Author-email: appleidqiufeng@outlook.com
Requires-Python: >=3.7,<4.0
Classifier: License :: OSI Approved :: MIT License
Classifier: Operating System :: OS Independent
Classifier: Programming Language :: Python :: 3
Classifier: Programming Language :: Python :: 3.7
Classifier: Programming Language :: Python :: 3.8
Classifier: Programming Language :: Python :: 3.9
Classifier: Programming Language :: Python :: 3.10
Classifier: Programming Language :: Python :: 3.11
Classifier: Programming Language :: Python :: 3.12
Classifier: Programming Language :: Python :: 3.13
Classifier: Programming Language :: Python :: 3.14
Project-URL: Changelog, https://github.com/qiufengcute/PyListenerTool/blob/main/CHANGELOG.md
Project-URL: Homepage, https://github.com/qiufengcute/PyListenerTool
Project-URL: Repository, https://github.com/qiufengcute/PyListenerTool
